README.rst
setup.cfg
setup.py
putlocker/__init__.py
putlocker/putlocker.py
putlocker.egg-info/PKG-INFO
putlocker.egg-info/SOURCES.txt
putlocker.egg-info/dependency_links.txt
putlocker.egg-info/entry_points.txt
putlocker.egg-info/requires.txt
putlocker.egg-info/top_level.txt