Metadata-Version: 1.1
Name: putlocker
Version: 1.0
Summary: Grabber app to get meta-data or download the movie from Putlocker. Website Putlocker: http://putlockers.ch
Home-page: https://github.com/agusmakmun/putlocker/
Author: Summon Agus
Author-email: agus@python.web.id
License: MIT
Download-URL: https://github.com/agusmakmun/putlocker/tarball/v1.0
Keywords: putlocker,putlocker downloader,putlocker grabber
Platform: Linux
Classifier: Development Status :: 5 - Production/Stable
Classifier: License :: OSI Approved :: MIT License
Classifier: Operating System :: POSIX :: Linux
Classifier: Intended Audience :: Developers
Classifier: Intended Audience :: End Users/Desktop
Classifier: Programming Language :: Python :: 2
Classifier: Programming Language :: Python :: 2.6
Classifier: Programming Language :: Python :: 2.7
Classifier: Programming Language :: Python :: 3
Classifier: Programming Language :: Python :: 3.3
Classifier: Programming Language :: Python :: 3.5
Classifier: Topic :: Internet
Classifier: Topic :: Utilities
